sphinx_versioned/__init__.py
sphinx_versioned/__main__.py
sphinx_versioned/_version.py
sphinx_versioned/build.py
sphinx_versioned/lib.py
sphinx_versioned/sphinx_.py
sphinx_versioned/versions.py
sphinx_versioned/_static/_rst_properties.css
sphinx_versioned/_static/_rtd_versions.js
sphinx_versioned/_static/badge_only.css
sphinx_versioned/_static/fontawesome-webfont.woff
sphinx_versioned/_templates/versions.html
sphinx_versioned_docs-1.4.dist-info/LICENSE
sphinx_versioned_docs-1.4.dist-info/METADATA
sphinx_versioned_docs-1.4.dist-info/WHEEL
sphinx_versioned_docs-1.4.dist-info/entry_points.txt
sphinx_versioned_docs-1.4.dist-info/top_level.txt
sphinx_versioned_docs-1.4.dist-info/RECORD
