Metadata-Version: 2.1
Name: sphinx-versioned-docs
Version: 1.4
Summary: Sphinx extension to build versionsed docs.
Home-page: https://github.com/devanshshukla99/sphinx-versioned-docs
Author: devanshshukla99
Author-email: devanshshukla99@outlook.com
License: MIT
Platform: UNKNOWN
Classifier: Development Status :: 5 - Production/Stable
Classifier: Environment :: Console
Classifier: Framework :: Sphinx :: Extension
Classifier: Intended Audience :: Developers
Classifier: License :: OSI Approved :: MIT License
Classifier: Operating System :: POSIX :: Linux
Classifier: Operating System :: Unix
Classifier: Operating System :: MacOS
Classifier: Programming Language :: Python :: 3.8
Classifier: Programming Language :: Python :: 3.9
Classifier: Programming Language :: Python :: 3.10
Classifier: Topic :: Documentation :: Sphinx
Classifier: Topic :: Software Development :: Documentation
Requires-Python: >=3.7
Requires-Dist: GitPython>=3.1.31
Requires-Dist: loguru>=0.7.0
Requires-Dist: setuptools>=66.0.0
Requires-Dist: sphinx>=4.6.0
Requires-Dist: typer>=0.9.0
Requires-Dist: rich
Provides-Extra: all
Requires-Dist: sphinx-versioned-docs[docs]; extra == "all"
Requires-Dist: sphinx-versioned-docs[tests]; extra == "all"
Provides-Extra: docs
Requires-Dist: sphinx-automodapi>=0.13; extra == "docs"
Requires-Dist: sphinx-rtd-theme; extra == "docs"
Provides-Extra: tests
Requires-Dist: pytest; extra == "tests"
Requires-Dist: beautifulsoup4; extra == "tests"
